dockertidy/__init__.py
dockertidy/autostop.py
dockertidy/cli.py
dockertidy/config.py
dockertidy/exception.py
dockertidy/garbage_collector.py
dockertidy/logger.py
dockertidy/parser.py
dockertidy/test/__init__.py
dockertidy/test/fixtures/__init__.py
dockertidy/test/fixtures/fixtures.py
dockertidy/test/unit/test_autostop.py
dockertidy/test/unit/test_garbagecollector.py
dockertidy/utils.py
docker_tidy-4.1.3.dist-info/METADATA
docker_tidy-4.1.3.dist-info/WHEEL
docker_tidy-4.1.3.dist-info/entry_points.txt
docker_tidy-4.1.3.dist-info/licenses/LICENSE
docker_tidy-4.1.3.dist-info/RECORD
