Metadata-Version: 2.4
Name: docker-tidy
Version: 4.1.3
Summary: Keep docker hosts tidy.
License: Apache-2.0
License-File: LICENSE
Keywords: docker,gc,prune,garbage
Author: Robert Kaussow
Author-email: mail@thegeeklab.de
Requires-Python: >=3.11.0,<4.0.0
Classifier: Development Status :: 5 - Production/Stable
Classifier: Environment :: Console
Classifier: Intended Audience :: Developers
Classifier: Intended Audience :: Information Technology
Classifier: Intended Audience :: System Administrators
Classifier: License :: OSI Approved :: Apache Software License
Classifier: Natural Language :: English
Classifier: Operating System :: POSIX
Classifier: Programming Language :: Python :: 3
Classifier: Programming Language :: Python :: 3.11
Classifier: Programming Language :: Python :: 3.12
Classifier: Programming Language :: Python :: 3.13
Classifier: Programming Language :: Python :: 3.14
Classifier: Topic :: Software Development
Classifier: Topic :: System :: Systems Administration
Classifier: Topic :: Utilities
Requires-Dist: anyconfig (==0.14.0)
Requires-Dist: appdirs (==1.4.4)
Requires-Dist: certifi (==2026.1.4)
Requires-Dist: colorama (==0.4.6)
Requires-Dist: dateparser (==1.2.2)
Requires-Dist: docker (==7.1.0)
Requires-Dist: docker-pycreds (==0.4.0)
Requires-Dist: environs (==14.5.0)
Requires-Dist: idna (==3.11)
Requires-Dist: ipaddress (==1.0.23)
Requires-Dist: jsonschema (==4.26.0)
Requires-Dist: nested-lookup (==0.2.25)
Requires-Dist: pathspec (==1.0.3)
Requires-Dist: python-dateutil (==2.9.0.post0)
Requires-Dist: python-json-logger (==4.0.0)
Requires-Dist: requests (==2.32.5)
Requires-Dist: ruamel.yaml (==0.19.1)
Requires-Dist: websocket_client (==1.9.0)
Requires-Dist: zipp (==3.23.0)
Project-URL: Documentation, https://docker-tidy.geekdocs.de/
Project-URL: Homepage, https://docker-tidy.geekdocs.de/
Project-URL: Repository, https://github.com/thegeeklab/docker-tidy/
